{
  "minecraft:adventure/sleep_in_bed": {
    "criteria": {
      "slept_in_bed": "2020-02-26 10:48:43 +0100"
    },
    "done": true
  },
  "minecraft:recipes/transportation/acacia_boat": {
    "criteria": {
      "in_water": "2020-02-26 10:47:50 +0100"
    },
    "done": true
  },
  "minecraft:recipes/transportation/oak_boat": {
    "criteria": {
      "in_water": "2020-02-26 10:47:50 +0100"
    },
    "done": true
  },
  "minecraft:recipes/transportation/dark_oak_boat": {
    "criteria": {
      "in_water": "2020-02-26 10:47:50 +0100"
    },
    "done": true
  },
  "minecraft:recipes/transportation/birch_boat": {
    "criteria": {
      "in_water": "2020-02-26 10:47:50 +0100"
    },
    "done": true
  },
  "minecraft:recipes/transportation/jungle_boat": {
    "criteria": {
      "in_water": "2020-02-26 10:47:50 +0100"
    },
    "done": true
  },
  "minecraft:recipes/transportation/spruce_boat": {
    "criteria": {
      "in_water": "2020-02-26 10:47:50 +0100"
    },
    "done": true
  },
  "minecraft:adventure/adventuring_time": {
    "criteria": {
      "minecraft:taiga": "2020-02-26 10:47:42 +0100",
      "minecraft:beach": "2020-02-26 10:48:16 +0100",
      "minecraft:river": "2020-02-26 10:48:05 +0100"
    },
    "done": false
  },
  "DataVersion": 2230
}